SimbioReader/__init__.py
SimbioReader/__main__.py
SimbioReader/cli.py
SimbioReader/constants.py
SimbioReader/exceptions.py
SimbioReader/filters.py
SimbioReader/filters_tools.py
SimbioReader/infocli.py
SimbioReader/phases.py
SimbioReader/simbioInfo.py
SimbioReader/sr.py
SimbioReader/subphases.py
SimbioReader/tests.py
SimbioReader/tools.py
SimbioReader/version.py
simbioreader-0.6.1.dist-info/licenses/LICENSE
simbioreader-0.6.1.dist-info/METADATA
simbioreader-0.6.1.dist-info/WHEEL
simbioreader-0.6.1.dist-info/entry_points.txt
simbioreader-0.6.1.dist-info/top_level.txt
simbioreader-0.6.1.dist-info/RECORD
