Metadata-Version: 2.4
Name: SimbioReader
Version: 0.6.1
Summary: Python Reader for the data from SIMBIO-SYS instrument suite on-board the ESA mission BepiColombo
Author-email: Romolo Politi <Romolo.Politi@inaf.it>
Project-URL: Repository, https://github.com/SIMBIO-SYS/SimbioReader
Keywords: data reader,Space Mission,BepiColombo,SIMBIO-SYS
Classifier: Programming Language :: Python :: 3.11
Classifier: Programming Language :: Python :: 3.12
Classifier: Programming Language :: Python :: 3.13
Classifier: Programming Language :: Python :: 3.14
Classifier: Development Status :: 4 - Beta
Requires-Python: >=3.11
License-File: LICENSE
Requires-Dist: numpy<3.0.0,>=2.3.3
Requires-Dist: pandas<3.0.0,>=2.3.2
Requires-Dist: rich-click<2.0.0,>=1.8.9
Requires-Dist: update-checker<0.19.0,>=0.18.0
Requires-Dist: importlib-metadata<9.0.0,>=8.7.0
Requires-Dist: pillow<13.0.0,>=12.0.0
Provides-Extra: docs
Requires-Dist: sphinx; extra == "docs"
Dynamic: license-file
